{
    "definition": {
        "$schema": "https://schema.management.azure.com/providers/Microsoft.Logic/schemas/2016-06-01/workflowdefinition.json#",
        "contentVersion": "1.0.0.0",
        "triggers": {
            "When_events_are_available_in_Event_Hub": {
                "type": "ApiConnection",
                "inputs": {
                    "host": {
                        "connection": {
                            "name": "@parameters('$connections')['eventhubs-1']['connectionId']"
                        }
                    },
                    "method": "get",
                    "path": "/@{encodeURIComponent('yellowtaxieventhub')}/events/batch/head",
                    "queries": {
                        "contentType": "application/json",
                        "consumerGroupName": "$Default",
                        "maximumEventsCount": 10
                    }
                },
                "recurrence": {
                    "interval": 1,
                    "frequency": "Minute"
                }
            }
        },
        "actions": {
            "cst8917-lab4-analyze_trip": {
                "type": "Function",
                "inputs": {
                    "body": "@triggerBody()",
                    "method": "POST",
                    "function": {
                        "id": "/subscriptions/07de8b92-8a0e-462b-9b32-7bfdaf51200e/resourceGroups/cst8917-lab4/providers/Microsoft.Web/sites/cst8917-lab4/functions/analyze_trip"
                    }
                },
                "runAfter": {}
            },
            "For_each": {
                "type": "Foreach",
                "foreach": "@body('cst8917-lab4-analyze_trip')",
                "actions": {
                    "Condition": {
                        "type": "If",
                        "expression": {
                            "and": [
                                {
                                    "equals": [
                                        "@items('For_each')?['isInteresting']",
                                        true
                                    ]
                                }
                            ]
                        },
                        "actions": {
                            "Condition_1": {
                                "type": "If",
                                "expression": {
                                    "and": [
                                        {
                                            "equals": [
                                                "@contains(items('For_each')?['insights'], 'SuspiciousVendorActivity')",
                                                true
                                            ]
                                        }
                                    ]
                                },
                                "actions": {
                                    "Post_cards_for_sus": {
                                        "type": "ApiConnection",
                                        "inputs": {
                                            "host": {
                                                "connection": {
                                                    "name": "@parameters('$connections')['teams']['connectionId']"
                                                }
                                            },
                                            "method": "post",
                                            "body": {
                                                "recipient": "lu000217@algonquinlive.com",
                                                "messageBody": "  {\n  \"type\": \"AdaptiveCard\",\n  \"body\": [\n    {\n      \"type\": \"TextBlock\",\n      \"text\": \"⚠️ Suspicious Vendor Activity Detected\",\n      \"weight\": \"Bolder\",\n      \"size\": \"Large\",\n      \"color\": \"Attention\"\n    },\n    {\n      \"type\": \"FactSet\",\n      \"facts\": [\n        { \"title\": \"Vendor\", \"value\": \"@{items('For_each')?['vendorID']}\" },\n        { \"title\": \"Distance (mi)\", \"value\": \"@{items('For_each')?['tripDistance']}\" },\n        { \"title\": \"Passengers\", \"value\": \"@{items('For_each')?['passengerCount']}\" },\n        { \"title\": \"Payment\", \"value\": \"@{items('For_each')?['paymentType']}\" },\n        { \"title\": \"Insights\", \"value\": \"@{join(items('For_each')?['insights'], ', ')}\" }\n      ]\n    }\n  ],\n  \"actions\": [],\n  \"version\": \"1.2\"\n}"
                                            },
                                            "path": "/v1.0/teams/conversation/adaptivecard/poster/Flow bot/location/@{encodeURIComponent('Chat with Flow bot')}"
                                        }
                                    }
                                },
                                "else": {
                                    "actions": {
                                        "Post_cards_for_interesting": {
                                            "type": "ApiConnection",
                                            "inputs": {
                                                "host": {
                                                    "connection": {
                                                        "name": "@parameters('$connections')['teams']['connectionId']"
                                                    }
                                                },
                                                "method": "post",
                                                "body": {
                                                    "recipient": "lu000217@algonquinlive.com",
                                                    "messageBody": "  {\n  \"type\": \"AdaptiveCard\",\n  \"body\": [\n    {\n      \"type\": \"TextBlock\",\n      \"text\": \"🚨 Interesting Trip Detected\",\n      \"weight\": \"Bolder\",\n      \"size\": \"Large\",\n      \"color\": \"Attention\"\n    },\n    {\n      \"type\": \"FactSet\",\n      \"facts\": [\n        { \"title\": \"Vendor\", \"value\": \"@{items('For_each')?['vendorID']}\" },\n        { \"title\": \"Distance (mi)\", \"value\": \"@{items('For_each')?['tripDistance']}\" },\n        { \"title\": \"Passengers\", \"value\": \"@{items('For_each')?['passengerCount']}\" },\n        { \"title\": \"Payment\", \"value\": \"@{items('For_each')?['paymentType']}\" },\n        { \"title\": \"Insights\", \"value\": \"@{join(items('For_each')?['insights'], ', ')}\" }\n      ]\n    }\n  ],\n  \"actions\": [],\n  \"version\": \"1.2\"\n}"
                                                },
                                                "path": "/v1.0/teams/conversation/adaptivecard/poster/Flow bot/location/@{encodeURIComponent('Chat with Flow bot')}"
                                            }
                                        }
                                    }
                                }
                            }
                        },
                        "else": {
                            "actions": {
                                "Post_card_for_no-instesting": {
                                    "type": "ApiConnection",
                                    "inputs": {
                                        "host": {
                                            "connection": {
                                                "name": "@parameters('$connections')['teams']['connectionId']"
                                            }
                                        },
                                        "method": "post",
                                        "body": {
                                            "recipient": "lu000217@algonquinlive.com",
                                            "messageBody": "  {\n  \"type\": \"AdaptiveCard\",\n  \"body\": [\n    {\n      \"type\": \"TextBlock\",\n      \"text\": \"✅ Trip Analyzed - No Issues\",\n      \"weight\": \"Bolder\",\n      \"size\": \"Large\",\n      \"color\": \"Good\"\n    },\n    {\n      \"type\": \"FactSet\",\n      \"facts\": [\n        { \"title\": \"Vendor\", \"value\": \"@{items('For_each')?['vendorID']}\" },\n        { \"title\": \"Distance (mi)\", \"value\": \"@{items('For_each')?['tripDistance']}\" },\n        { \"title\": \"Passengers\", \"value\": \"@{items('For_each')?['passengerCount']}\" },\n        { \"title\": \"Payment\", \"value\": \"@{items('For_each')?['paymentType']}\" },\n        { \"title\": \"Summary\", \"value\": \"@{items('For_each')?['summary']}\" }\n      ]\n    }\n  ],\n  \"actions\": [],\n  \"version\": \"1.2\"\n}"
                                        },
                                        "path": "/v1.0/teams/conversation/adaptivecard/poster/Flow bot/location/@{encodeURIComponent('Chat with Flow bot')}"
                                    }
                                }
                            }
                        }
                    }
                },
                "runAfter": {
                    "cst8917-lab4-analyze_trip": [
                        "Succeeded"
                    ]
                }
            }
        },
        "outputs": {},
        "parameters": {
            "$connections": {
                "type": "Object",
                "defaultValue": {}
            }
        }
    },
    "parameters": {
        "$connections": {
            "type": "Object",
            "value": {
                "eventhubs-1": {
                    "id": "/subscriptions/07de8b92-8a0e-462b-9b32-7bfdaf51200e/providers/Microsoft.Web/locations/canadacentral/managedApis/eventhubs",
                    "connectionId": "/subscriptions/07de8b92-8a0e-462b-9b32-7bfdaf51200e/resourceGroups/cst8917-lab4/providers/Microsoft.Web/connections/eventhubs-1",
                    "connectionName": "eventhubs-1"
                },
                "teams": {
                    "id": "/subscriptions/07de8b92-8a0e-462b-9b32-7bfdaf51200e/providers/Microsoft.Web/locations/canadacentral/managedApis/teams",
                    "connectionId": "/subscriptions/07de8b92-8a0e-462b-9b32-7bfdaf51200e/resourceGroups/cst8917-lab4/providers/Microsoft.Web/connections/teams",
                    "connectionName": "teams"
                }
            }
        }
    }
}